__init__.py
vegvisir/__init__.py
vegvisir/main.py
vegvisir-0.0.1.dist-info/LICENSE.md
vegvisir-0.0.1.dist-info/METADATA
vegvisir-0.0.1.dist-info/WHEEL
vegvisir-0.0.1.dist-info/top_level.txt
vegvisir-0.0.1.dist-info/RECORD
